Arqui/Labs/Week2/tests/maquina_de_estados.v
module mi_fsm(input clk, input bit, output reg [1:0] estado_salida);
  
  parameter ESTADO_0 = 2'b00, ESTADO_1 = 2'b01, ESTADO_2 = 2'b10, ESTADO_3 = 2'b11;
  
  always @ (posedge clk) begin
    case (estado_salida)
      ESTADO_0: begin
        if (bit == 1) begin
          estado_salida <= ESTADO_1;
        end else begin
          estado_salida <= ESTADO_0;
        end
      end
      
      ESTADO_1: begin
        if (bit == 1) begin
          estado_salida <= ESTADO_2;
        end else begin
          estado_salida <= ESTADO_0;
        end
      end
      
      ESTADO_2: begin
        if (bit == 1) begin
          estado_salida <= ESTADO_3;
        end else begin
          estado_salida <= ESTADO_0;
        end
      end
      
      ESTADO_3: begin
        estado_salida <= ESTADO_0;
      end
      
      default: estado_salida <= ESTADO_0;
    endcase
  end
  
endmodule

Arqui/Labs/Week2/tests/maquina_de_estados_tb.v
`timescale 1ns / 1ns
module mi_maquina_estados_tb;

    reg clk, bit;
    wire [1:0]estado_salida;

mi_fsm test1(.clk(clk), .bit(bit), .estado_salida(estado_salida));

initial begin
    clk = 0;
    forever #1 clk=~clk;
    end

initial begin
    bit = 1;
    #1
    $display ("bit=%b, salida=%b",bit,estado_salida);
    #1
    bit = 1;
    #1
    $display ("bit=%b, salida=%b",bit,estado_salida);
    #1
    bit = 0;
    #1
    $display ("bit=%b, salida=%b",bit,estado_salida);
    #1
    bit = 1;
    #1
    $display ("bit=%b, salida=%b",bit,estado_salida);
    #1
    bit = 1;
    #1
    $display ("bit=%b, salida=%b",bit,estado_salida);
    #1
    bit = 1;
    #1
    $display ("bit=%b, salida=%b",bit,estado_salida);
    #1
    bit = 1;
    #1
    $display ("bit=%b, salida=%b",bit,estado_salida);
    #1
    bit = 1;
    #1
    $display ("bit=%b, salida=%b",bit,estado_salida);
    #1
    
    $finish;
    end

initial begin
    $dumpfile("maquina_de_estados.vcd");
    $dumpvars;
end
endmodule

Arqui/Labs/Week2/tests/maquina_de_estados.vcd
$date
	Wed Apr 26 17:10:26 2023
$end
$version
	Icarus Verilog
$end
$timescale
	1ps
$end
$scope module mi_maquina_estados_tb $end
$var wire 2 ! estado_salida [1:0] $end
$var reg 1 " bit $end
$var reg 1 # clk $end
$scope module test1 $end
$var wire 1 " bit $end
$var wire 1 # clk $end
$var reg 2 $ estado_salida [1:0] $end
$upscope $end
$upscope $end
$enddefinitions $end
#0
$dumpvars
bx $
0#
1"
bx !
$end
#1000
b0 !
b0 $
1#
#2000
0#
#3000
b1 !
b1 $
1#
#4000
0"
0#
#5000
b0 !
b0 $
1#
#6000
1"
0#
#7000
b1 !
b1 $
1#
#8000
0#
#9000
b10 !
b10 $
1#
#10000
0#
#11000
b11 !
b11 $
1#
#12000
0#
#13000
b0 !
b0 $
1#
#14000
0#
#15000
b1 !
b1 $
1#
