Arqui/Labs/Week5/ME_LAB/ME.v
module m_e(clk, direction, estado_salida);

    input clk;
    input [1:0]direction;
    output reg [5:0]estado_salida;

    reg [5:0] ESTADO_PREV;

    parameter ESTADO_0 = 6'b000_000,
    ESTADO_1 = 6'b000_100,
    ESTADO_2 = 6'b000_110,
    ESTADO_3 = 6'b000_111,
    ESTADO_4 = 6'b001_000,
    ESTADO_5 = 6'b011_000,
    ESTADO_6 = 6'b111_000;


    always @ (posedge clk) begin

    case(estado_salida)    
        ESTADO_0:begin
            if (direction == 2'b01)begin
                estado_salida <= ESTADO_1;
                // ESTADO_PREV <= ESTADO_0;
            end else if (direction == 2'b10)begin
                estado_salida <= ESTADO_4;
                // ESTADO_PREV <= ESTADO_0;
            end else begin
                estado_salida <=  ESTADO_0;
            end    
            ESTADO_PREV <= ESTADO_0;
        end

        ESTADO_1:begin
            if (ESTADO_PREV == ESTADO_0)begin
                estado_salida <= ESTADO_2;
                // ESTADO_PREV <= ESTADO_1;
            end else if(ESTADO_PREV == ESTADO_2)begin
                estado_salida <= ESTADO_0;
                // ESTADO_PREV <= ESTADO_1;
            end
            ESTADO_PREV <= ESTADO_1;
            
        end

        ESTADO_2:begin
            if (ESTADO_PREV == ESTADO_1)begin
                estado_salida <= ESTADO_3;
                // ESTADO_PREV <= ESTADO_2;
            end else if(ESTADO_PREV == ESTADO_3)begin
                estado_salida <= ESTADO_1;
                // ESTADO_PREV <= ESTADO_2;
            end
            ESTADO_PREV <= ESTADO_2;
        end

        ESTADO_3:begin
            if (direction == 2'b01)begin
                estado_salida <= ESTADO_3;
            end else begin
                estado_salida <= ESTADO_2;
            end
            ESTADO_PREV <= ESTADO_3;
        end

        ESTADO_4:begin
            if (ESTADO_PREV == ESTADO_0)begin
                estado_salida <= ESTADO_4;
                // ESTADO_PREV <= ESTADO_1;
            end else if(ESTADO_PREV == ESTADO_5)begin
                estado_salida <= ESTADO_0;
                // ESTADO_PREV <= ESTADO_1;
            end
            ESTADO_PREV <= ESTADO_4;
        end

        ESTADO_5:begin
            if (ESTADO_PREV == ESTADO_4)begin
                estado_salida <= ESTADO_6;
                // ESTADO_PREV <= ESTADO_1;
            end else if(ESTADO_PREV == ESTADO_6)begin
                estado_salida <= ESTADO_4;
                // ESTADO_PREV <= ESTADO_1;
            end
            ESTADO_PREV <= ESTADO_5;
        end

        ESTADO_6:begin
            if (direction == 2'b10)begin
                estado_salida <= ESTADO_6;
            end else begin
                estado_salida <= ESTADO_5;
            end
            ESTADO_PREV <= ESTADO_6;
        end

        default: estado_salida <= ESTADO_0;
    endcase
        
    end

endmodule

Arqui/Labs/Week5/ME_LAB/ME_tb.v
`timescale 1ns / 1ns
module ME_tb;


    reg clk;
    reg [1:0]direction;
    wire [5:0]estado_salida;

    m_e test1(.clk(clk),.direction(direction),.estado_salida(estado_salida));

    initial begin
        clk = 0;
        forever #1 clk=~clk;
    end

    initial begin 
        direction = 2'b01;
        #1
        $display ("direction=%b, e_salida=%b",direction,estado_salida);
        #1

        // direction = 2'b01;
        #1
        $display ("direction=%b, e_salida=%b",direction,estado_salida);
        #1
                direction = 2'b00;

        // direction = 2'b01;
        #1
        $display ("direction=%b, e_salida=%b",direction,estado_salida);
        #1
        // direction = 2'b01;
        #1
        $display ("direction=%b, e_salida=%b",direction,estado_salida);
        #1

        #1
        $display ("direction=%b, e_salida=%b",direction,estado_salida);
        #1

        #1
        $display ("direction=%b, e_salida=%b",direction,estado_salida);
        #1

        #1
        $display ("direction=%b, e_salida=%b",direction,estado_salida);
        #1

        #1
        $display ("direction=%b, e_salida=%b",direction,estado_salida);
        #1

        #1
        $display ("direction=%b, e_salida=%b",direction,estado_salida);
        #1

        $finish;

    end


    initial begin
    $dumpfile("m_e.vcd");
    $dumpvars;
    end 

endmodule

Arqui/Labs/Week5/ME_LAB/m_e.vcd
$date
	Thu Apr 27 11:13:12 2023
$end
$version
	Icarus Verilog
$end
$timescale
	1ns
$end
$scope module ME_tb $end
$var wire 6 ! estado_salida [5:0] $end
$var reg 1 " clk $end
$var reg 2 # direction [1:0] $end
$scope module test1 $end
$var wire 1 " clk $end
$var wire 2 $ direction [1:0] $end
$var reg 6 % ESTADO_PREV [5:0] $end
$var reg 6 & estado_salida [5:0] $end
$upscope $end
$upscope $end
$enddefinitions $end
#0
$dumpvars
bx &
bx %
b1 $
b1 #
0"
bx !
$end
#1
b0 !
b0 &
1"
#2
0"
#3
b0 %
b100 !
b100 &
1"
#4
b0 #
b0 $
0"
#5
b100 %
b110 !
b110 &
1"
#6
0"
#7
b110 %
b111 !
b111 &
1"
#8
0"
#9
b111 %
b110 !
b110 &
1"
#10
0"
#11
b110 %
b100 !
b100 &
1"
#12
0"
#13
b100 %
b0 !
b0 &
1"
#14
0"
#15
b0 %
1"
