Arqui/Labs/solved2/mux_21_bh.v

module mux21_bh(y , s , d0, d1);
input s,d0,d1;
output y;
/*if(s==1b0) begin
    y=d0;
end
else begin
    y=d1;
    // y=d0 or d1;
end*/

assign y=(s==1'b0)?d0:d1;

endmodule

Arqui/Labs/solved2/Mux21_tb.v
`include "mux_21_bh.v"
`timescale 1ns/1ns
module  mux_21_tb;
wire out;
reg d0, d1, s;
mux21_bh name(.y(out), .d0(d0), .d1(d1), .s(s));
initial
begin
$dumpfile("mux21_bh_tb.vcd");
$dumpvars(0,mux_21_tb);
d0=1'b0;
d1=1'b0;
s=1'b0;
#100 $finish;
end
always #40 d0=~d0; // always #40 s2=~s0
always #20 d1=~d1; // always #20 s1=~s1
always #10 s=~s; // always #10 s0=~s0
always@(d0 or d1 or s)
$monitor("At time = %t, Output = %d", $time, out);
endmodule;

Arqui/Labs/solved2/mux21_bh_tb.vcd
$date
	Thu Apr 13 23:53:36 2023
$end
$version
	Icarus Verilog
$end
$timescale
	1ns
$end
$scope module mux_21_tb $end
$var wire 1 ! out $end
$var reg 1 " d0 $end
$var reg 1 # d1 $end
$var reg 1 $ s $end
$scope module name $end
$var wire 1 " d0 $end
$var wire 1 # d1 $end
$var wire 1 $ s $end
$var wire 1 ! y $end
$upscope $end
$upscope $end
$enddefinitions $end
#0
$dumpvars
0$
0#
0"
0!
$end
#10
1$
#20
0!
0$
1#
#30
1!
1$
#40
1!
0$
0#
1"
#50
0!
1$
#60
1!
0$
1#
#70
1$
#80
0!
0$
0#
0"
#90
1$
#100
0!
0$
1#
