Arqui/Labs/Week2/rs_latch/rs_latch.v

module rs_latch_behavioral(r,s,q,qn,clk);

  input r,s,clk;
  output reg q,qn;
  
  always @(posedge clk)
  begin
    if (r == 0 && s == 0)
    begin
      q <= q;
      qn <= qn;
    end

    else if (r == 0 && s == 1)
    begin
      q <= 1;
      qn <= 0;
    end
    else if (r == 1 && s == 0)
    begin
      q <= 0;
      qn <= 1;
    end

    else if (r == 1 && s == 1)
    begin
      q <= 1'bZ;
      qn <= 1'bZ;
    end
  end
  
//   always @(posedge clk)
//     qn <= ~q;

endmodule

Arqui/Labs/Week2/rs_latch/rs_latch_tb.v
`timescale 1ns / 1ps
module rs_latch_behavioral_tb;
    reg r,s,clk;
    wire q,qn;

    rs_latch_behavioral rs_test(.r(r),.s(s),.q(q),.qn(qn),.clk(clk));

  	initial begin
  		clk=0;
        forever #1 clk=~clk;
    end

    initial begin
    r=1; s=1;
    #1 
    $display ("r=%b, s=%b, q=%b, qn=%b",r,s,q,qn);
    #1
    r=0; s=1;
    #1 
    $display ("r=%b, s=%b, q=%b, qn=%b",r,s,q,qn);
    #1
    r=1; s=1; 
    #1
    $display ("r=%b, s=%b, q=%b, qn=%b",r,s,q,qn);
    #1
    r=1; s=0; 
    #1
    $display ("r=%b, s=%b, q=%b, qn=%b",r,s,q,qn);
    #1
    r=0; s=0; 
    #1
    $display ("r=%b, s=%b, q=%b, qn=%b",r,s,q,qn);
    #1     
    $finish;
  end

  initial begin
    $dumpfile("rs_latch_behavioral.vcd");
    $dumpvars;
  end
endmodule

Arqui/Labs/Week2/rs_latch/rs_latch_behavioral.vcd
$date
	Wed Apr 26 15:23:28 2023
$end
$version
	Icarus Verilog
$end
$timescale
	1ps
$end
$scope module rs_latch_behavioral_tb $end
$var wire 1 ! qn $end
$var wire 1 " q $end
$var reg 1 # clk $end
$var reg 1 $ r $end
$var reg 1 % s $end
$scope module rs_test $end
$var wire 1 # clk $end
$var wire 1 $ r $end
$var wire 1 % s $end
$var reg 1 " q $end
$var reg 1 ! qn $end
$upscope $end
$upscope $end
$enddefinitions $end
#0
$dumpvars
1%
1$
0#
x"
x!
$end
#1000
z!
z"
1#
#2000
0$
0#
#3000
0!
1"
1#
#4000
1$
0#
#5000
z!
z"
1#
#6000
0%
0#
#7000
1!
0"
1#
#8000
0$
0#
