Arqui/Labs/Week5/gated_D_latch/gated_D_latch.v
module gated_D_latch(WE, D, Q, Qn);

    input WE;
    input D;
    output reg Q,Qn;

    always @ (*)
    begin
        if (WE == 1) begin
            Q <= D;
            Qn <= ~D;
        end
    end
endmodule

Arqui/Labs/Week5/gated_D_latch/gated_D_latch_tb.v
`timescale 1ns / 1ns

module gated_D_latch_tb;
    reg WE;
    reg D;
    wire Q;
    wire Qn;

    gated_D_latch test(.WE(WE),.D(D),.Q(Q),.Qn(Qn));

    initial begin
        WE=1; D=1;
        #1 
        $display ("WE=%b, D=%b, Q=%b, QN=%b",WE,D,Q,Qn);
        #1
        WE=1; D=0;
        #1 
        $display ("WE=%b, D=%b, Q=%b, QN=%b",WE,D,Q,Qn);
        #1
        WE=0; D=1;
        #1 
        $display ("WE=%b, D=%b, Q=%b, QN=%b",WE,D,Q,Qn);
        #1
        WE=0; D=0;
        #1 
        $display ("WE=%b, D=%b, Q=%b, QN=%b",WE,D,Q,Qn);
        #1
        WE=1; D=1;
        #1 
        $display ("WE=%b, D=%b, Q=%b, QN=%b",WE,D,Q,Qn);
        #1
        WE=0; D=0;
        #1 
        $display ("WE=%b, D=%b, Q=%b, QN=%b",WE,D,Q,Qn);
        #1
        WE=0; D=1;
        #1 
        $display ("WE=%b, D=%b, Q=%b, QN=%b",WE,D,Q,Qn);
        #1
        WE=0; D=0;
        #1 
        $finish;
    end


    initial begin
    $dumpfile("gated_D_latch.vcd");
    $dumpvars;
    end
endmodule

Arqui/Labs/Week5/gated_D_latch/gated_D_latch.vcd
$date
	Thu Apr 27 17:18:59 2023
$end
$version
	Icarus Verilog
$end
$timescale
	1ns
$end
$scope module gated_D_latch_tb $end
$var wire 1 ! Qn $end
$var wire 1 " Q $end
$var reg 1 # D $end
$var reg 1 $ WE $end
$scope module test $end
$var wire 1 # D $end
$var wire 1 $ WE $end
$var reg 1 " Q $end
$var reg 1 ! Qn $end
$upscope $end
$upscope $end
$enddefinitions $end
#0
$dumpvars
1$
1#
1"
0!
$end
#2
1!
0"
0#
#4
1#
0$
#6
0#
#8
0!
1"
1#
1$
#10
0#
0$
#12
1#
#14
0#
